data_drift_detector/__init__.py
data_drift_detector/data_drift_detector.py
data_drift_detector-0.0.18.dist-info/LICENSE
data_drift_detector-0.0.18.dist-info/METADATA
data_drift_detector-0.0.18.dist-info/WHEEL
data_drift_detector-0.0.18.dist-info/top_level.txt
data_drift_detector-0.0.18.dist-info/RECORD
