Metadata-Version: 2.1
Name: data-drift-detector
Version: 0.0.18
Summary: Compare differences between 2 datasets to identify data drift
Home-page: https://github.com/kelvnt/data-drift-detector
Author: Kelvin Tay
Author-email: btkelvin@gmail.com
License: GPLv3
Requires-Python: >=3.6.0
License-File: LICENSE
Requires-Dist: category-encoders >=2.2.2
Requires-Dist: matplotlib >=3.4.3
Requires-Dist: numpy >=1.19.0
Requires-Dist: pandas >=1.0.0
Requires-Dist: scikit-learn >=0.24.1
Requires-Dist: scipy >=1.5.4
Requires-Dist: seaborn >=0.11.2
